asrch/#arson.py#
asrch/Logs/logo
asrch/__init__.py
asrch/__main__.py
asrch/commands/__init__.py
asrch/commands/_find.py
asrch/commands/_open.py
asrch/commands/_quizlet.py
asrch/commands/_send.py
asrch/commands/_whois.py
asrch/commands/no_driver/__init__.py
asrch/commands/no_driver/_nd_find.py
asrch/commands/no_driver/_nd_open.py
asrch/commands/no_driver/_nd_quizlet.py
asrch/commands/no_driver/_nd_send.py
asrch/commands/no_driver/_nd_whois.py
asrch/commands/no_driver/py.typed
asrch/config/basic.toml
asrch/config/current_ws.toml
asrch/config/current_ws.txt
asrch/config/discrete.toml
asrch/config/quick.toml
asrch/config/tomltest.py
asrch/config/undetected.toml
asrch/config/workspaces.txt
asrch/downloaded_files/dashboard.lock
asrch/modules/__init__.py
asrch/modules/_formatting.py
asrch/modules/fun/__init__.py
asrch/modules/fun/_pets.py
asrch/modules/logging_formatter.py
asrch/py.typed
asrch/requirements.txt
asrch/tests/__init__.py
asrch/tests/nd_tests/__init__.py
asrch/tests/nd_tests/test_nd_open.py
asrch/tests/nd_tests/test_nd_search.py
asrch/tests/selenium_tests/__init__.py
asrch/tests/selenium_tests/test_find.py
asrch/tests/selenium_tests/test_open.py
asrch/tests/selenium_tests/test_send.py
asrch/tests/test_logger_test.py
asrch/utils/__init__.py
asrch/utils/constants.py
asrch/webdriver/__init__.py
asrch/webdriver/webdriver_manager.py
asrch-7.8.1.dist-info/LICENSE
asrch-7.8.1.dist-info/METADATA
asrch-7.8.1.dist-info/WHEEL
asrch-7.8.1.dist-info/entry_points.txt
asrch-7.8.1.dist-info/RECORD
