Metadata-Version: 2.1
Name: asrch
Version: 7.8.1
Summary: A terminal based webscraper and browser
License: MIT
Author: j
Requires-Python: >=3.12,<4.0
Classifier: License :: OSI Approved :: MIT License
Classifier: Programming Language :: Python :: 3
Classifier: Programming Language :: Python :: 3.12
Requires-Dist: asrch_ascli (>=1.0.0,<2.0.0)
Requires-Dist: bs4 (>=0.0.2,<0.0.3)
Requires-Dist: requests (>=2.32.3,<3.0.0)
Requires-Dist: selenium (>=4.21.0,<5.0.0)
Requires-Dist: toml (>=0.10.2,<0.11.0)
Requires-Dist: typer[all] (>=0.12.3,<0.13.0)
